i2c_gui2/__init__.py
i2c_gui2/entry_points.py
i2c_gui2/etroc1_gui.py
i2c_gui2/etroc2_gui.py
i2c_gui2/functions.py
i2c_gui2/i2c_connection_helper.py
i2c_gui2/i2c_messages.py
i2c_gui2/i2c_usb_iss_helper.py
i2c_gui2/chips/__init__.py
i2c_gui2/chips/ad5593r_chip.py
i2c_gui2/chips/address_space_controller.py
i2c_gui2/chips/base_chip.py
i2c_gui2/chips/etroc1_chip.py
i2c_gui2/chips/etroc2_chip.py
i2c_gui2/gui/about.py
i2c_gui2/gui/logging.py
i2c_gui2-0.1.14.dist-info/METADATA
i2c_gui2-0.1.14.dist-info/WHEEL
i2c_gui2-0.1.14.dist-info/entry_points.txt
i2c_gui2-0.1.14.dist-info/licenses/AUTHORS.rst
i2c_gui2-0.1.14.dist-info/licenses/LICENSE
i2c_gui2-0.1.14.dist-info/RECORD
